{"id":353711,"titlu":"Trofeu Personalizat – Cadou pentru sotie","slug":"personalizare-trofeu-cadou-pentru-sotie","descriere":"<h2>Trofeu Personalizat – Cadou pentru sotie</h2>\r\n&nbsp;\r\n<h2>Un Mesaj de Iubire Capturat în Detalii</h2>\r\nAcest trofeu personalizat, cu dimensiunile elegante de 18x22 cm, este realizat cu atenție pentru a reflecta emoțiile tale sincere. Fiecare detaliu al acestuia vorbește despre natura unică a relației voastre, fiind un simbol perfect al iubirii. Materialele premium folosite aduc un aer de eleganță, amintind de momentele speciale pe care le sărbătoriți împreună. Perfect pentru a fi oferit cu ocazia zilei îndrăgostiților sau a aniversărilor, acest cadou a fost apreciat de mulți, fiind îmbogățit de recenzii pozitive de la cumpărători fericiți care au ales să-și exprime sentimentele printr-un cadou deosebit.","descriere_scurta":"<h2>Un Cadou Special pentru Momente Unice</h2>\r\nOferirea unui cadou personalizat pentru soția ta este o modalitate superbă de a-i arăta cât de mult o apreciezi. În momente speciale, cum ar fi ziua îndrăgostiților sau aniversările, un trofeu personalizat devine simbolul unei iubiri profunde și a unor amintiri de neuitat.","pret":"120","pret_redus":null,"end_sale":null,"imagine_principala":{"full":"https://darurialese.com/wp-content/uploads/2022/06/personalizare-trofeu-cadou-pentru-sotie.jpg","300x300":"https://darurialese.com/wp-content/uploads/2022/06/personalizare-trofeu-cadou-pentru-sotie-300x300.jpg","100x100":"https://darurialese.com/wp-content/uploads/2022/06/personalizare-trofeu-cadou-pentru-sotie-150x150.jpg"},"galerie":[],"rating":"5.00","vanzari":7,"dimensiune":{"lungime":"22","latime":"1","inaltime":"18"},"nr_recenzii":1,"average_recenzii":"5.00","taguri":[{"nume":"cadou cu fotografie pentru sotie","slug":"cadou-cu-fotografie-pentru-sotie"},{"nume":"cadou deosebit pentru sotie","slug":"cadou-deosebit-pentru-sotie"},{"nume":"cadou elegant pentru sotie","slug":"cadou-elegant-pentru-sotie"},{"nume":"cadou pentru aniversare relatie","slug":"cadou-pentru-aniversare-relatie"},{"nume":"cadou pentru soție","slug":"cadou-pentru-sotie"},{"nume":"cadou personalizat cu gravura","slug":"cadou-personalizat-cu-gravura"},{"nume":"cadou personalizat sotie","slug":"cadou-personalizat-sotie"},{"nume":"cadou romantic pentru sotie","slug":"cadou-romantic-pentru-sotie"},{"nume":"cadou simbol al iubirii","slug":"cadou-simbol-al-iubirii"},{"nume":"cadou sotie aniversare casatorie","slug":"cadou-sotie-aniversare-casatorie"},{"nume":"cadou sotie ziua indragostitilor","slug":"cadou-sotie-ziua-indragostitilor"},{"nume":"cadou special pentru ziua sotiei","slug":"cadou-special-pentru-ziua-sotiei"},{"nume":"decor personalizat pentru casa","slug":"decor-personalizat-pentru-casa"},{"nume":"idei cadouri pentru sotie","slug":"idei-cadouri-pentru-sotie"},{"nume":"suvenir personalizat pentru sotie","slug":"suvenir-personalizat-pentru-sotie"},{"nume":"trofeu cadou pentru sotie","slug":"trofeu-cadou-pentru-sotie"},{"nume":"trofeu cu dedicatie pentru sotie","slug":"trofeu-cu-dedicatie-pentru-sotie"},{"nume":"trofeu cu mesaj de dragoste","slug":"trofeu-cu-mesaj-de-dragoste"},{"nume":"trofeu cu mesaj pentru sotie","slug":"trofeu-cu-mesaj-pentru-sotie"},{"nume":"trofeu cu poza si text","slug":"trofeu-cu-poza-si-text"},{"nume":"trofeu gravare plexi","slug":"trofeu-gravare-plexi"},{"nume":"trofeu gravare wenge","slug":"trofeu-gravare-wenge"},{"nume":"trofeu gravat pentru sotie","slug":"trofeu-gravat-pentru-sotie"},{"nume":"trofeu iubita personalizat","slug":"trofeu-iubita-personalizat"},{"nume":"trofeu logodnica personalizat","slug":"trofeu-logodnica-personalizat"},{"nume":"trofeu pentru aniversare cuplu","slug":"trofeu-pentru-aniversare-cuplu"},{"nume":"trofeu personalizat sotie","slug":"trofeu-personalizat-sotie"},{"nume":"trofeu pfl wenge","slug":"trofeu-pfl-wenge"},{"nume":"trofeu plexiglas personalizat","slug":"trofeu-plexiglas-personalizat"},{"nume":"trofeu romantic personalizat","slug":"trofeu-romantic-personalizat"}],"attributes":[{"name":"Relatie","slug":"pa_cadouri-personalizate","visible":true,"variation":false,"options":["Iubita","Logodnica","Sotie"]},{"name":"Fotografie","slug":"pa_fotografie","visible":true,"variation":false,"options":["Da"]},{"name":"Material","slug":"pa_material","visible":true,"variation":false,"options":["PFL Wenge","Plexiglas"]},{"name":"Personalizare","slug":"pa_personalizare","visible":true,"variation":false,"options":["Gravare"]},{"name":"Seap","slug":"pa_seap","visible":true,"variation":false,"options":["inclus"]},{"name":"Tip","slug":"pa_tip","visible":true,"variation":false,"options":["Trofee"]},{"name":"Brand","slug":"pa_brand","visible":false,"variation":false,"options":["Daruri Alese"]},{"name":"PRODUCTIE","slug":"pa_productie","visible":false,"variation":false,"options":["Gravare Plexi","Gravare Wenge fiber"]}],"recenzii":[{"autor":"Vladimir Tulovei","data":"2022-06-07 15:51:47","rating":"5","continut":"A fost mai mult decat perfect, a ajuns la timp, bine realizat si echipa de nota 10\r\nRecomand","verified":false,"imagini":[]},{"autor":"Nacu Daniela","data":"","rating":0,"continut":"Foarte incantata de produs. A ajuns foarte  , iar voi sunteti cei mai buni. Cu siguranta voi reveni si cu alte comenzi.","verified":false,"imagini":[{"thumbnail":"https://darurialese.com/wp-content/uploads/2024/08/17243399136438117539242890445291-scaled.jpg","full":"https://darurialese.com/wp-content/uploads/2024/08/17243399136438117539242890445291-scaled.jpg"}]},{"autor":"conduraru.madalina","data":"","rating":0,"continut":"Mulțumită de calitatea produselor si pentru promptitudine.","verified":false,"imagini":[{"thumbnail":"https://darurialese.com/wp-content/uploads/2023/07/IMG_20230703_142257-scaled.jpg","full":"https://darurialese.com/wp-content/uploads/2023/07/IMG_20230703_142257-scaled.jpg"}]},{"autor":"Daniela Baiculescuu","data":"","rating":0,"continut":"superb!!","verified":false,"imagini":[{"thumbnail":"https://darurialese.com/wp-content/uploads/2022/05/WhatsApp-Image-2022-05-24-at-16.01.30-1.jpeg","full":"https://darurialese.com/wp-content/uploads/2022/05/WhatsApp-Image-2022-05-24-at-16.01.30-1.jpeg"}]},{"autor":"Golea Elena-Lidia","data":"","rating":0,"continut":"Foarte frumos a iesit, iar comanda a ajuns repede. Duminica seara am plasat comanda, luni am fost sunata pentru confirmare, marti pentru aprobarea graficii, iar miercuri a ajuns curierul. Sunt foarte mulțumită. Au dat dovada de profesionalism si seriozitate, cu siguranta voi mai comanda.","verified":false,"imagini":[{"thumbnail":"https://darurialese.com/wp-content/uploads/2021/12/20211222_174115-scaled.jpg","full":"https://darurialese.com/wp-content/uploads/2021/12/20211222_174115-scaled.jpg"}]},{"autor":"Lefter Flory","data":"","rating":0,"continut":"A ajuns comanda este superbă mulțumim ????????????????????????","verified":false,"imagini":[{"thumbnail":"https://darurialese.com/wp-content/uploads/2021/11/250838782_287374373242823_4737131756177241986_n.jpg","full":"https://darurialese.com/wp-content/uploads/2021/11/250838782_287374373242823_4737131756177241986_n.jpg"}]},{"autor":"Cristina Sauciuc","data":"","rating":0,"continut":"Foarte mulțumită. Recomand cu toată încrederea. Mulțumesc frumos ????❤️❤️","verified":false,"imagini":[{"thumbnail":"https://darurialese.com/wp-content/uploads/2021/05/71785897_2565094403582670_6539719802791919616_n.jpeg","full":"https://darurialese.com/wp-content/uploads/2021/05/71785897_2565094403582670_6539719802791919616_n.jpeg"}]},{"autor":"Mirela- Oana","data":"","rating":0,"continut":"Multumesc frumos","verified":false,"imagini":[{"thumbnail":"https://darurialese.com/wp-content/uploads/2020/03/68571124_1314058845423318_890565282756558848_n.jpg","full":"https://darurialese.com/wp-content/uploads/2020/03/68571124_1314058845423318_890565282756558848_n.jpg"}]},{"autor":"Margarit Francisca","data":"","rating":0,"continut":"Minunat!!!! Exact ca in pozaa!!! Iar comanda a ajuns foarte repede!! Recomand cu drag!!! Cu siguranta voi reveni !!","verified":false,"imagini":[{"thumbnail":"https://darurialese.com/wp-content/uploads/2024/04/8C53B75D-97E6-47F6-96AE-1AF2A258AA46-scaled.jpeg","full":"https://darurialese.com/wp-content/uploads/2024/04/8C53B75D-97E6-47F6-96AE-1AF2A258AA46-scaled.jpeg"}]},{"autor":"Conțescu Georgiana","data":"","rating":0,"continut":"Minunată! Recomand cu încredere! ????????","verified":false,"imagini":[{"thumbnail":"https://darurialese.com/wp-content/uploads/2024/03/1000002341-scaled.jpg","full":"https://darurialese.com/wp-content/uploads/2024/03/1000002341-scaled.jpg"}]},{"autor":"Tudor Cristina","data":"","rating":0,"continut":"O amintire minunată pentru nașica noastră!\r\nFoarte serioși, atenți la detalii, comanda a ajuns a doua zi după confirmare și chiar și  cu un mic cadou și pentru mamă. Mulțumim! ????","verified":false,"imagini":[{"thumbnail":"https://darurialese.com/wp-content/uploads/2023/06/IMG_20230623_184933.jpg","full":"https://darurialese.com/wp-content/uploads/2023/06/IMG_20230623_184933.jpg"}]},{"autor":"l_lavinia_86","data":"","rating":0,"continut":"Nu este prima data cand comand de la ei si asta datorita seriozitatii, promptitudinii si rapiditatii cu care livreaza produsele. Am ramas din nou placut surprinsa! Este exact cum imi doream! Felicitari si multumim pt ca faceti parte din viata noastra!","verified":false,"imagini":[{"thumbnail":"https://darurialese.com/wp-content/uploads/2025/04/20250411_113148.jpg","full":"https://darurialese.com/wp-content/uploads/2025/04/20250411_113148.jpg"}]},{"autor":"HOSPODE MADALINA","data":"","rating":0,"continut":"Un produs EXTRAORDINAR. Recomand cu toata increderea.","verified":false,"imagini":[{"thumbnail":"https://darurialese.com/wp-content/uploads/2023/12/WhatsApp-Image-2023-12-18-at-14.50.13.jpeg","full":"https://darurialese.com/wp-content/uploads/2023/12/WhatsApp-Image-2023-12-18-at-14.50.13.jpeg"}]},{"autor":"Paul Anamaria","data":"","rating":0,"continut":"Foarte mulțumită de produs. A ajuns foarte repede , iar voi sunteti cei mai buni. Cu siguranta voi reveni si cu alte comenzi.","verified":false,"imagini":[{"thumbnail":"https://darurialese.com/wp-content/uploads/2025/09/IMG_2157-scaled.jpeg","full":"https://darurialese.com/wp-content/uploads/2025/09/IMG_2157-scaled.jpeg"}]},{"autor":"Eremia Elena","data":"","rating":0,"continut":"Am ales acest cadou pentru copii mei, foarte frumos. Recomand!","verified":false,"imagini":[{"thumbnail":"https://darurialese.com/wp-content/uploads/2024/10/18-ani.jpg","full":"https://darurialese.com/wp-content/uploads/2024/10/18-ani.jpg"}]},{"autor":"Florean Daniela","data":"","rating":0,"continut":"Rapiditate, seriozitate. Am ales o poza care nu s-a potrivit, iar doamna care m-a sunat a fost jos pălăria. Totul lucrat asa de frumos, sigur revin cu o altă acomandă. Plus alte atenți puse în colet.","verified":false,"imagini":[{"thumbnail":"https://darurialese.com/wp-content/uploads/2023/10/16970274304802640485061781168957-scaled.jpg","full":"https://darurialese.com/wp-content/uploads/2023/10/16970274304802640485061781168957-scaled.jpg"}]},{"autor":"BODEA ELENA","data":"","rating":0,"continut":"WoooooW… Rapiditate, grafica frumoasă, totul arată impecabil! Il aaaaaaaaaaaaador !!","verified":false,"imagini":[{"thumbnail":"https://darurialese.com/wp-content/uploads/2023/10/WhatsApp-Image-2023-10-10-at-12.42.52.jpeg","full":"https://darurialese.com/wp-content/uploads/2023/10/WhatsApp-Image-2023-10-10-at-12.42.52.jpeg"}]},{"autor":"Irimie Ionela","data":"","rating":0,"continut":"WoW... Rapiditate, grafica frumoasă, totul arată impecabil! Imi place mult. Cu siguranță va fi o surpriză plăcută celor care o ofer cadou.","verified":false,"imagini":[{"thumbnail":"https://darurialese.com/wp-content/uploads/2022/06/IMG_20220623_170123.jpg","full":"https://darurialese.com/wp-content/uploads/2022/06/IMG_20220623_170123.jpg"}]},{"autor":"Novac Daniela","data":"","rating":0,"continut":"Un cadou minunat! O realizare perfecta, recomand cu toată încrederea,o echipa de profesioniști. Este a doua oară când fac comanda,sigur voi reveni și cu alte ocazii.","verified":false,"imagini":[{"thumbnail":"https://darurialese.com/wp-content/uploads/2023/08/IMG-20230805-WA0003-scaled.jpeg","full":"https://darurialese.com/wp-content/uploads/2023/08/IMG-20230805-WA0003-scaled.jpeg"}]},{"autor":"Ariciuc Cristina","data":"","rating":0,"continut":"Sunt foarte mulțumită de achiziție, livrare promptă, personal amabil si operativ.","verified":false,"imagini":[{"thumbnail":"https://darurialese.com/wp-content/uploads/2023/06/20230531_150318-scaled.jpg","full":"https://darurialese.com/wp-content/uploads/2023/06/20230531_150318-scaled.jpg"}]}],"personalizare":[{"type":"textfield","label":"Adresare","required":false,"enabled":true,"placeholder":"","options":[],"name":"62989a387b9855.96996562","price":"","price_type":"","min_chars":"","max_chars":"","description":"ex: Draga mea sotie"},{"type":"textfield","label":"Data","required":false,"enabled":true,"placeholder":"","options":[],"name":"62989a487b98a6.45514092","price":"","price_type":"","min_chars":"","max_chars":"","description":""},{"type":"upload","label":"Poza 1","required":false,"enabled":true,"placeholder":"","options":[],"name":"62989a3d7b9860.27842071","price":"","price_type":"","description":""},{"type":"textfield","label":"Nume 1","required":false,"enabled":true,"placeholder":"","options":[],"name":"62989a3f7b9875.46734323","price":"","price_type":"","min_chars":"","max_chars":"","description":""},{"type":"upload","label":"Poza 2","required":false,"enabled":true,"placeholder":"","options":[],"name":"62989a407b9886.10574077","price":"","price_type":"","description":""},{"type":"textfield","label":"Nume 2","required":false,"enabled":true,"placeholder":"","options":[],"name":"62989a437b9890.20866572","price":"","price_type":"","min_chars":"","max_chars":"","description":""},{"type":"checkboxes","label":"","required":false,"enabled":true,"placeholder":"","options":[],"name":"62989a547b98b8.37407665","description":""},{"type":"textarea","label":"Mesaj","required":false,"enabled":true,"placeholder":"","options":[],"name":"62989a597b98c9.30136640","price":"","price_type":"","min_chars":"","max_chars":"300","description":""},{"type":"textarea","label":"Observatii","required":false,"enabled":true,"placeholder":"","options":[],"name":"62989a5d7b98d7.58404791","price":"","price_type":"","min_chars":"","max_chars":"","description":""}],"texte-produs":[],"categorii":[{"id":97,"titlu":"Cadouri de ziua indragostitilor","slug":"cadouri-ziua-indragostitilor","imagine":"https://darurialese.ro/wp-content/uploads/2022/05/indragostiti-01.svg","produse":[{"id":59549,"titlu":"Trofeu pentru persoana iubita – LED multicolor si poza","slug":"trofeu-pentru-persoana-iubita-led-multicolor-si-poza","descriere":"Esti in cautarea unui <a href=\"https://darurialese.ro/cadou/cadou-personalizat/\">trofeu personalizat</a> cu LED si poza pentru ziua indragostitilor? Te putem ajuta cu un cadou personalizat care sa ii arate cat de mult inseamna pentru tine.\r\n\r\nCateodata, nu avem nevoie de declaratii lungi de dragoste, pentru a ne arata sentimentele fata de persoana de langa noi. Cel mai important este ca aceste cuvinte sa fie spuse din suflet. Acest cadou personalizat este o dovada a iubirii care va impresiona cu siguranta.\r\n\r\nAcest cadou personalizat cu led este modul potrivit prin care sa iti exprimi cel mai frumos \" Te iubesc\". Sunt doar doua cuvinte, dar care au o importanta semnificatie pentru cei indragostiti. Personalizam acest cadou inedit cu poza voastra preferata, pentru a ramane o amintire de neuitat.\r\n\r\nVrei sa iti surprinzi persoana iubita cu un cadou, dar nu ai nicio idee? Iti oferim acest trofeu personalizat cu led cu numele voastre si fotografia preferata, care sigur ii va lumina ziua si va fi profund recunoscatoare.\r\n\r\nVa trimitem acest cadouri oriunde doriti dumneavoastra, in orice oras sau sat din tara. Sustinem iubirea din orice coltisor de tara.\r\n\r\nIubirea este un sentiment frumos, care va coloreaza viata si sufletele. Acest trofeu cu led multicolor va va incanta cu lumina sa, in functie de culoarea care va place.\r\n\r\nProdusul este creat special pentru indragostiti, pentru a va ajuta sa va exprimati iubirea fata de persoana de langa voi. Se personalizeaza cu numele si data aniversarii, pentru a fi un cadou unic si simblic.\r\n\r\n&nbsp;\r\n\r\nPoti vizualiza parerea clientilor  care au achizitionat un trofeu personalizat cu LED si poza pentru ziua indragostitilor de la noi pe <a href=\"https://facebook.com/darurialese\">Daruri Alese.</a>","descriere_scurta":"","pret":"135","pret_redus":"109","end_sale":"2026-01-31 23:59:59","imagine_principala":{"full":"https://darurialese.com/wp-content/uploads/2019/11/cadou-pentru-persoana-iubita-led-1200x1200.jpg","300x300":"https://darurialese.com/wp-content/uploads/2019/11/cadou-pentru-persoana-iubita-led-1200x1200-300x300.jpg","100x100":"https://darurialese.com/wp-content/uploads/2019/11/cadou-pentru-persoana-iubita-led-1200x1200-100x100.jpg"},"galerie":[{"full":"https://darurialese.com/wp-content/uploads/2019/11/3.jpg","300x300":"https://darurialese.com/wp-content/uploads/2019/11/3-300x300.jpg","100x100":"https://darurialese.com/wp-content/uploads/2019/11/3-100x100.jpg"},{"full":"https://darurialese.com/wp-content/uploads/2019/11/cadou-pentru-persoana-iubita-scaled.jpg","300x300":"https://darurialese.com/wp-content/uploads/2019/11/cadou-pentru-persoana-iubita-300x300.jpg","100x100":"https://darurialese.com/wp-content/uploads/2019/11/cadou-pentru-persoana-iubita-100x100.jpg"},{"full":"https://darurialese.com/wp-content/uploads/2019/11/1.jpg","300x300":"https://darurialese.com/wp-content/uploads/2019/11/1-300x300.jpg","100x100":"https://darurialese.com/wp-content/uploads/2019/11/1-100x100.jpg"}],"rating":"4.99","vanzari":4667,"dimensiune":{"lungime":"18","latime":"1","inaltime":"20.5"},"nr_recenzii":104,"average_recenzii":"4.99"},{"id":59595,"titlu":"Cadou personalizat – Trofeu pentru ziua indragostitilor","slug":"cadou-personalizat-trofeu-pentru-ziua-indragostitilor","descriere":"Esti in cautarea unui cadou personalizat pentru ziua indragostitilor? Iti oferim acest cadou care cu siguranta va impresiona persoana iubita!\r\n\r\nIubirea este un sentiment unic, prin care iti arati afectiunea si respectul fata de omul care iti e alaturi zi de zi!\r\n\r\nPersoana iubita este omul care iti este alaturi mereu, neconditionat, care te sprijina in orice decizie ai lua. Ea te iubeste si te sustine pe tot parcurusul timpului. Tocmai de aceea, iti oferim ocazia sa ii spui cat de mult o iubesti intr-un mod unic. Acest cadou poate fi unul cu adevarat special, deoarece poate fi personalizat cu declaratia de dragoste proprie, spusa exact folosind cuvintele tale. Mai mult de atat, putem personaliza trofeul cu poza voastra preferata pentru a fi un cadou simbolic, creat special pentru voi. Suntem convinsi ca reactia la primirea cadoului va fi una pe masura asteptarilor tale.\r\n\r\nCe este foarte special la acest cadou, este faptul ca el va ramane o amintire frumoasa de-a lungul anilor. De fiecare data cand va fi privit va va aminti ca iubirea ce o purtati a rezistat in timp.\r\n\r\nAcest trofeu personalizat pentru el sau ea poate fi oferit pentru ziua indragostilor, aniversarea relatiei, ziua de nastere a iubitei sau iubitului, sau chiar fara un motiv special. Ii poti aminti cat de mult o iubesti fara sa fie o ocazie speciala, asa surpriza va fi una si mai apreciata.\r\n<h5>Spune-i \" Te iubesc!\" intr-un mod unic!</h5>\r\nNoi ne ocupam sa livram coletul oriunde in tara! Dorim ca fiecare dintre voi sa aiba ocazia sa ofere acest cadou minunat persoanei iubite.\r\n\r\nInca nu esti convins daca sa il comanzi? Vezi parerea clientilor care au comandat acest cadou personalizat pentru ziua indragostitilor pe <a href=\"https://www.facebook.com/darurialese\">Daruri Alese</a>. Va stam la dispozitie cu orice informatie doriti sa aflati! Va asteptam cu mare drag!\r\n\r\n&nbsp;","descriere_scurta":"","pret":"120","pret_redus":null,"end_sale":null,"imagine_principala":{"full":"https://darurialese.com/wp-content/uploads/2020/01/trofeu-ziua-indragostitilor-1200x1200.jpg","300x300":"https://darurialese.com/wp-content/uploads/2020/01/trofeu-ziua-indragostitilor-1200x1200-300x300.jpg","100x100":"https://darurialese.com/wp-content/uploads/2020/01/trofeu-ziua-indragostitilor-1200x1200-100x100.jpg"},"galerie":[],"rating":"5.00","vanzari":1101,"dimensiune":{"lungime":"18","latime":"1","inaltime":"19"},"nr_recenzii":49,"average_recenzii":"5.00"},{"id":59658,"titlu":"Cadou personalizat Trofeu LED – Iubitului meu","slug":"cadou-personalizat-trofeu-led-iubitului-meu","descriere":"Esti in cautarea unui <a href=\"https://darurialese.ro/cadou/cadou-personalizat/\">cadou personalizat</a> pentru iubit sau pentru iubita? Te putem ajuta cu un trofeu personalizat cu un mesaj care va impresiona cu siguranta.\r\n\r\nCu totii cautam cadoul perfect pentru ziua indragostitilor, pentru aniversarea relatiei sau doar sa ii faci o surpriza persoanei iubite. Acest model de trofeu cu LED este perfect pentru a-i transmite cat de frumoasa este dragostea voastra. Poti surprinde prin a scrie un mesaj despre insemnatatea unui moment anume, o traire unica in cuplu, sau sentimentele pe care i le porti.\r\n\r\nAcest trofeu personalizat este unul care sa simbolizeze recunostinta pe ca i-o porti iubitei tale. Il putem personaliza cu declaratia sentimentelor dumneavoastra, pentru a crea un cadou unic. Suntem foarte siguri ca acest cadou o va impresiona pana la lacrimi.\r\n\r\nDragostea este cel mai frumos sentiment de pe pamant. Arata-i recunostinta sotului tau, oferindu-i un cadou inedit, personalizat cu declaratia ta de dragoste.\r\n<h5>Lumineaza-i ziua sotiei tale, oferindu-i un cadou personalizat luminos care sa o surprinda si sa-i aduca zambetul pe chip.</h5>\r\nNu este nevoie sa astepti ziua indragostitilor sau aniversarea casatoriei pentru a-i arata sotiei recunostinta ta. O poti face oricand, deoarece iubirea se sarbatoreste in fiecare zi. Aminteste-i sotiei tale cat de mult apreciezi existenta ei in viata ta si cat de mult o iubesti.\r\n\r\nAcest cadou personalizat cu LED pentru iubit este metoda perfecta sa ii oferi un dar iubitului, aratandu-i recunostinta ta pentru el si iubirea ce-o porti in suflet. Acesta placheta poate fi personalizata cu textul tau si numele voastre, lucru ce il transforma intr-un cadou unic.\r\n\r\nLivram cadourile personalizate in orice oras, in orice sat din tara. In acest mod, va ajutam sa oferiti cadoul potrivit pentru iubit/iubita, oriunde locuiti.\r\n\r\nPoti vedea parerea clientilor care deja au achizitionat un cadou personalizat pentru iubit de la noi pe <a href=\"https://www.facebook.com/darurialese/\">Daruri Alese</a>.","descriere_scurta":"","pret":"120","pret_redus":"109","end_sale":"2026-01-31 23:59:59","imagine_principala":{"full":"https://darurialese.com/wp-content/uploads/nano-banana/LED817833-INDRAGOSTITI/cadou_personalizat_trofeu_led_iubitului_meu_rosu.png","300x300":"https://darurialese.com/wp-content/uploads/nano-banana/LED817833-INDRAGOSTITI/cadou_personalizat_trofeu_led_iubitului_meu_rosu-300x300.png","100x100":"https://darurialese.com/wp-content/uploads/nano-banana/LED817833-INDRAGOSTITI/cadou_personalizat_trofeu_led_iubitului_meu_rosu-150x150.png"},"galerie":[{"full":"https://darurialese.com/wp-content/uploads/nano-banana/LED817833-INDRAGOSTITI/cadou_personalizat_trofeu_led_iubitului_meu_poza_luminata.png","300x300":"https://darurialese.com/wp-content/uploads/nano-banana/LED817833-INDRAGOSTITI/cadou_personalizat_trofeu_led_iubitului_meu_poza_luminata-300x300.png","100x100":"https://darurialese.com/wp-content/uploads/nano-banana/LED817833-INDRAGOSTITI/cadou_personalizat_trofeu_led_iubitului_meu_poza_luminata-150x150.png"},{"full":"https://darurialese.com/wp-content/uploads/nano-banana/LED817833-INDRAGOSTITI/cadou_personalizat_trofeu_led_iubitului_meu_albastru.png","300x300":"https://darurialese.com/wp-content/uploads/nano-banana/LED817833-INDRAGOSTITI/cadou_personalizat_trofeu_led_iubitului_meu_albastru-300x300.png","100x100":"https://darurialese.com/wp-content/uploads/nano-banana/LED817833-INDRAGOSTITI/cadou_personalizat_trofeu_led_iubitului_meu_albastru-150x150.png"},{"full":"https://darurialese.com/wp-content/uploads/nano-banana/LED817833-INDRAGOSTITI/cadou_personalizat_trofeu_led_iubitului_meu_verde.png","300x300":"https://darurialese.com/wp-content/uploads/nano-banana/LED817833-INDRAGOSTITI/cadou_personalizat_trofeu_led_iubitului_meu_verde-300x300.png","100x100":"https://darurialese.com/wp-content/uploads/nano-banana/LED817833-INDRAGOSTITI/cadou_personalizat_trofeu_led_iubitului_meu_verde-150x150.png"},{"full":"https://darurialese.com/wp-content/uploads/nano-banana/LED817833-INDRAGOSTITI/cadou_personalizat_trofeu_led_iubitului_meu_mov.png","300x300":"https://darurialese.com/wp-content/uploads/nano-banana/LED817833-INDRAGOSTITI/cadou_personalizat_trofeu_led_iubitului_meu_mov-300x300.png","100x100":"https://darurialese.com/wp-content/uploads/nano-banana/LED817833-INDRAGOSTITI/cadou_personalizat_trofeu_led_iubitului_meu_mov-150x150.png"},{"full":"https://darurialese.com/wp-content/uploads/2020/03/cadou-personalizat-iubitului-meu1.jpg","300x300":"https://darurialese.com/wp-content/uploads/2020/03/cadou-personalizat-iubitului-meu1-300x300.jpg","100x100":"https://darurialese.com/wp-content/uploads/2020/03/cadou-personalizat-iubitului-meu1-100x100.jpg"}],"rating":"5.00","vanzari":1040,"dimensiune":{"lungime":"17.5","latime":"1","inaltime":"24"},"nr_recenzii":41,"average_recenzii":"5.00"},{"id":59612,"titlu":"Trofeu LED - Cadou personalizat inimioara pentru persoana iubita","slug":"cadou-personalizat-trofeu-led-inimioara-pentru-persoana-iubita","descriere":"Esti in cautarea unui <a href=\"https://darurialese.ro/cadou/cadou-personalizat/\">cadou personalizat</a> pentru persoana iubita, dar esti in pana de idei? Noi iti oferim cadoul perfect, personalizat cu mesajul dorit, care va impresiona cu siguranta.\r\n\r\nIubirea este un sentiment minunat, trait de toata lumea! Insa, fiecare poveste de dragoste este unica si speciala in felul ei! Fie ca v-ati intalnit acum o luna, un an, sau chiar mai multi, fiecare aniversare este un prilej de a sarbatori si de a va face amintiri minunate impreuna!\r\n\r\nInsa, ce te faci atunci cand ai epuizat toate ideile, si nu mai gasesti niciun cadou pentru ea sau cadou pentru el?\r\n\r\nIn acele momente grele, echipa Daruri alese iti sare in ajutor! Ca cadou ar putea fi mai potrivit decat un cadou personalizat pentru persoana iubita? Trofeele noastre pot fi personalizate cu orice mesaj sau fotografie doriti.  In acest mod, va oferim libertatea de a darui un cadou cu adevarat special!\r\nPentru ca acest trofeu personalizat sa patrunda adanc in sufletul persoanei care il va primi, si pentru a atinge emotii puternice, puteti transmite o poveste traita impreuna, un moment anume, cu o insemnatate foarte mare. Sau niste ganduri din suflet pentru persoana ce iti face zilele mai frumoase!\r\n\r\nCert este, ca orice alegere veti face, nu aveti cum sa dati gres! Va stam la dispozitie intotdeauna pentru a oferi, nu doar cadouri personalizate, ci si amintiri minunate.\r\n<h5>Dragostea se traieste in doi! Surprinde persoana de langa tine cu un cadou la fel de special ca si ea!</h5>\r\nDaca inca nu te-am convins, poti vedea parerea integrala a clientilor care deja au achizitionat un cadou personalizat de la noi pe <a href=\"https://facebook.com/darurialese\">Daruri Alese.</a>\r\n\r\nAlege acel cadou personalizat pentru persoana iubita care ii va face cu siguranta ziua mai frumoasa! Nu doar in ziua ce l-a primit, ci in fiecare zi ce va urma dupa aceea! Nimic nu ii aduce un zambet mai mare pe buze, decat o asemenea surpriza din partea persoanei preferate.","descriere_scurta":"<h2>Alege un trofeu led personalizat pentru persoana iubita!</h2>\r\nUn trofeu personalizat cu leduri poate fi un cadou minunat pentru persoana iubita. Acest trofeu poate fi personalizat cu numele si data alegerii voastre de a fi impreuna, astfel incat sa devina o amintire speciala a tuturor lucrurilor minunate pe care le-ati realizat impreuna.\r\n\r\nAcest trofeu poate fi pastrat intr-un loc special din casa voastra, astfel incat sa devina un element important al decorului si sa va aduca aminte de tot ceea ce inseamna iubirea pentru voi. Indiferent de modul in care alegi sa il personalizezi, un trofeu cu leduri poate fi un cadou deosebit pentru persoana iubita, prin care sa arati cat de mult inseamna pentru tine si cat de mult apreciezi tot ceea ce faceti impreuna.","pret":"120","pret_redus":"109","end_sale":"2026-01-31 23:59:59","imagine_principala":{"full":"https://darurialese.com/wp-content/uploads/nano-banana/LEDINIMIOARA-INDRAGOSTITI/trofeu_led_8211_cadou_personalizat_inimioara_pentru_persoana_iubita_rosu.png","300x300":"https://darurialese.com/wp-content/uploads/nano-banana/LEDINIMIOARA-INDRAGOSTITI/trofeu_led_8211_cadou_personalizat_inimioara_pentru_persoana_iubita_rosu-300x300.png","100x100":"https://darurialese.com/wp-content/uploads/nano-banana/LEDINIMIOARA-INDRAGOSTITI/trofeu_led_8211_cadou_personalizat_inimioara_pentru_persoana_iubita_rosu-150x150.png"},"galerie":[{"full":"https://darurialese.com/wp-content/uploads/2019/10/trofeu-led-indragostiti-albastru.jpg","300x300":"https://darurialese.com/wp-content/uploads/2019/10/trofeu-led-indragostiti-albastru-300x300.jpg","100x100":"https://darurialese.com/wp-content/uploads/2019/10/trofeu-led-indragostiti-albastru-100x100.jpg"},{"full":"https://darurialese.com/wp-content/uploads/2019/10/trofeu-led-indragostiti-roz.jpg","300x300":"https://darurialese.com/wp-content/uploads/2019/10/trofeu-led-indragostiti-roz-300x300.jpg","100x100":"https://darurialese.com/wp-content/uploads/2019/10/trofeu-led-indragostiti-roz-100x100.jpg"},{"full":"https://darurialese.com/wp-content/uploads/nano-banana/LEDINIMIOARA-INDRAGOSTITI/trofeu_led_8211_cadou_personalizat_inimioara_pentru_persoana_iubita_poza_luminata.png","300x300":"https://darurialese.com/wp-content/uploads/nano-banana/LEDINIMIOARA-INDRAGOSTITI/trofeu_led_8211_cadou_personalizat_inimioara_pentru_persoana_iubita_poza_luminata-300x300.png","100x100":"https://darurialese.com/wp-content/uploads/nano-banana/LEDINIMIOARA-INDRAGOSTITI/trofeu_led_8211_cadou_personalizat_inimioara_pentru_persoana_iubita_poza_luminata-150x150.png"},{"full":"https://darurialese.com/wp-content/uploads/nano-banana/LEDINIMIOARA-INDRAGOSTITI/trofeu_led_8211_cadou_personalizat_inimioara_pentru_persoana_iubita_albastru.png","300x300":"https://darurialese.com/wp-content/uploads/nano-banana/LEDINIMIOARA-INDRAGOSTITI/trofeu_led_8211_cadou_personalizat_inimioara_pentru_persoana_iubita_albastru-300x300.png","100x100":"https://darurialese.com/wp-content/uploads/nano-banana/LEDINIMIOARA-INDRAGOSTITI/trofeu_led_8211_cadou_personalizat_inimioara_pentru_persoana_iubita_albastru-150x150.png"},{"full":"https://darurialese.com/wp-content/uploads/nano-banana/LEDINIMIOARA-INDRAGOSTITI/trofeu_led_8211_cadou_personalizat_inimioara_pentru_persoana_iubita_verde.png","300x300":"https://darurialese.com/wp-content/uploads/nano-banana/LEDINIMIOARA-INDRAGOSTITI/trofeu_led_8211_cadou_personalizat_inimioara_pentru_persoana_iubita_verde-300x300.png","100x100":"https://darurialese.com/wp-content/uploads/nano-banana/LEDINIMIOARA-INDRAGOSTITI/trofeu_led_8211_cadou_personalizat_inimioara_pentru_persoana_iubita_verde-150x150.png"},{"full":"https://darurialese.com/wp-content/uploads/nano-banana/LEDINIMIOARA-INDRAGOSTITI/trofeu_led_8211_cadou_personalizat_inimioara_pentru_persoana_iubita_mov.png","300x300":"https://darurialese.com/wp-content/uploads/nano-banana/LEDINIMIOARA-INDRAGOSTITI/trofeu_led_8211_cadou_personalizat_inimioara_pentru_persoana_iubita_mov-300x300.png","100x100":"https://darurialese.com/wp-content/uploads/nano-banana/LEDINIMIOARA-INDRAGOSTITI/trofeu_led_8211_cadou_personalizat_inimioara_pentru_persoana_iubita_mov-150x150.png"},{"full":"https://darurialese.com/wp-content/uploads/2019/10/trofeu-led-indragostiti-1200x1139.jpg","300x300":"https://darurialese.com/wp-content/uploads/2019/10/trofeu-led-indragostiti-1200x1139-300x300.jpg","100x100":"https://darurialese.com/wp-content/uploads/2019/10/trofeu-led-indragostiti-1200x1139-100x100.jpg"}],"rating":"4.96","vanzari":837,"dimensiune":{"lungime":"18.5","latime":"1","inaltime":"19"},"nr_recenzii":23,"average_recenzii":"4.96"},{"id":3282,"titlu":"Cadou personalizat Trofeu led - Placheta inima mea - LED","slug":"placheta-inima-mea-led","descriere":"Esti in cautarea unui <a href=\"https://darurialese.ro/cadou/cadou-personalizat/\">cadou personalizat</a> pentru aniversare, dar esti in pana de idei? Noi iti oferim cadoul perfect, personalizat cu mesajul dorit, care va impresiona cu siguranta.\r\n\r\nEste destul de greu sa gasesti un cadou care sa transmita un mesaj, o emotie! In ziua de astazi avem la un click distanta tot felul de idei de cadouri. Insa cum putem sa stim ca am ales cadoul potrivit? Gusturile difera de la persoana la persoana, de aceea alegerea unui cadou ne poate pune in dificultate.\r\n<h5>Iubirea sta in lucrurile mici!</h5>\r\nAniversarea voastra, fie ca este a unui an impreuna, sau a mai multora, este un prilej de a celebra iubirea!\r\n\r\nUn cadou, fie el cat de mic, este special cand transmite un sentiment! Insa, poate face asta doar cand este daruit din suflet! Un simplu obiect, scump sau ieftin, oricat de util sau frumos ar fi,  este un simplu obiect. Acest lucru se schimba doar in momentul in care transmite o emotie. Un cadou personalizat pentru aniversare va deveni, dintr-un simplu lucru, o amintire vie a unor momente minunate impartasite de voi doi.\r\n<h5>Nu uita de personalizare!</h5>\r\nDesi suntem aici pentru a te ajuta sa gasesti un mesaj potrivit pentru ocazia speciala pe care o sarbatoresti, vom accepta cu siguranta si o sugestie din partea ta! Iti stam la dispozitie cu sugestii si idei de texte ce pot fi gravate pe minunata inimioara pe care doresti sa o cumperi.  Dar totusi, daca ai alte planuri si doresti un mesaj mai personal, sau niste ganduri pentru persoana iubita, stai fara grija! Textul este personalizabil, astfel avand la dispozitie un cadou foarte maleabil.\r\n<h5>Doresti o anumita culoare?</h5>\r\nStai fara grija! Sunt incluse toate cele trei culori ale LED-ului (rosu, albastru si mov). Acestea se pot schimba prin apasarea succesiva a butonului atasat firului de priza!\r\n\r\nVezi parerea integrala a clientilor care deja au achizitionat un cadou personalizat de la noi pe <a href=\"https://facebook.com/darurialese\">Daruri Alese</a>","descriere_scurta":"","pret":"120","pret_redus":"109","end_sale":"2026-01-31 23:59:59","imagine_principala":{"full":"https://darurialese.com/wp-content/uploads/nano-banana/8993773/cadou_personalizat_trofeu_led_8211_placheta_inima_mea_8211_led_mov.png","300x300":"https://darurialese.com/wp-content/uploads/nano-banana/8993773/cadou_personalizat_trofeu_led_8211_placheta_inima_mea_8211_led_mov-300x300.png","100x100":"https://darurialese.com/wp-content/uploads/nano-banana/8993773/cadou_personalizat_trofeu_led_8211_placheta_inima_mea_8211_led_mov-150x150.png"},"galerie":[{"full":"https://darurialese.com/wp-content/uploads/2019/01/culoare-mov.jpg","300x300":"https://darurialese.com/wp-content/uploads/2019/01/culoare-mov-300x300.jpg","100x100":"https://darurialese.com/wp-content/uploads/2019/01/culoare-mov-100x100.jpg"},{"full":"https://darurialese.com/wp-content/uploads/2019/01/culoare-albastra.jpg","300x300":"https://darurialese.com/wp-content/uploads/2019/01/culoare-albastra-300x300.jpg","100x100":"https://darurialese.com/wp-content/uploads/2019/01/culoare-albastra-100x100.jpg"},{"full":"https://darurialese.com/wp-content/uploads/nano-banana/8993773/cadou_personalizat_trofeu_led_8211_placheta_inima_mea_8211_led_poza_luminata.png","300x300":"https://darurialese.com/wp-content/uploads/nano-banana/8993773/cadou_personalizat_trofeu_led_8211_placheta_inima_mea_8211_led_poza_luminata-300x300.png","100x100":"https://darurialese.com/wp-content/uploads/nano-banana/8993773/cadou_personalizat_trofeu_led_8211_placheta_inima_mea_8211_led_poza_luminata-150x150.png"},{"full":"https://darurialese.com/wp-content/uploads/nano-banana/8993773/cadou_personalizat_trofeu_led_8211_placheta_inima_mea_8211_led_rosu.png","300x300":"https://darurialese.com/wp-content/uploads/nano-banana/8993773/cadou_personalizat_trofeu_led_8211_placheta_inima_mea_8211_led_rosu-300x300.png","100x100":"https://darurialese.com/wp-content/uploads/nano-banana/8993773/cadou_personalizat_trofeu_led_8211_placheta_inima_mea_8211_led_rosu-150x150.png"},{"full":"https://darurialese.com/wp-content/uploads/nano-banana/8993773/cadou_personalizat_trofeu_led_8211_placheta_inima_mea_8211_led_albastru.png","300x300":"https://darurialese.com/wp-content/uploads/nano-banana/8993773/cadou_personalizat_trofeu_led_8211_placheta_inima_mea_8211_led_albastru-300x300.png","100x100":"https://darurialese.com/wp-content/uploads/nano-banana/8993773/cadou_personalizat_trofeu_led_8211_placheta_inima_mea_8211_led_albastru-150x150.png"},{"full":"https://darurialese.com/wp-content/uploads/nano-banana/8993773/cadou_personalizat_trofeu_led_8211_placheta_inima_mea_8211_led_verde.png","300x300":"https://darurialese.com/wp-content/uploads/nano-banana/8993773/cadou_personalizat_trofeu_led_8211_placheta_inima_mea_8211_led_verde-300x300.png","100x100":"https://darurialese.com/wp-content/uploads/nano-banana/8993773/cadou_personalizat_trofeu_led_8211_placheta_inima_mea_8211_led_verde-150x150.png"},{"full":"https://darurialese.com/wp-content/uploads/2019/01/49648165_2178490762196166_4253957492263878656_o-1200x1199.jpg","300x300":"https://darurialese.com/wp-content/uploads/2019/01/49648165_2178490762196166_4253957492263878656_o-1200x1199-300x300.jpg","100x100":"https://darurialese.com/wp-content/uploads/2019/01/49648165_2178490762196166_4253957492263878656_o-1200x1199-100x100.jpg"}],"rating":"4.91","vanzari":699,"dimensiune":{"lungime":"19","latime":"1","inaltime":"17.5"},"nr_recenzii":32,"average_recenzii":"4.91"}]},{"id":103,"titlu":"Cadouri pentru femei","slug":"cadouri-femeie-mama-sotie","imagine":"https://darurialese.ro/wp-content/uploads/2022/05/mama-01.svg","produse":[{"id":3330,"titlu":"Cadou personalizat Trofeu - La multi ani, mama!","slug":"la-multi-ani-mama","descriere":"Esti in cautarea unui <a href=\"https://darurialese.ro/cadou/cadou-personalizat/\">cadou personalizat</a> aniversare mama? Te putem ajuta cu un cadou personalizat cu poza si un mesaj prin care sa ii urezi “La multi ani”. Este modalitatea prin care sa ii arati recunostinta pe care i-o porti.\r\n\r\nCu totii consideram ca mama noastra este o persoana sfanta. Din acest motiv, de ziua ei, gandurile tale trebuie sa ajunga la ea in cel mai frumos mod posibil. Acest produs este conceput special pentru aceasta ocazie minunata si va fi apreciat cu siguranta!\r\n\r\nVezi parerea integrala a clientilor care deja au achizitionat un cadou personalizat aniversare mama de la noi pe <a href=\"https://facebook.com/darurialese\">Daruri Alese.</a>","descriere_scurta":"","pret":"120","pret_redus":"104","end_sale":"2026-01-31 23:59:59","imagine_principala":{"full":"https://darurialese.com/wp-content/uploads/2020/02/produs-mama-1.png","300x300":"https://darurialese.com/wp-content/uploads/2020/02/produs-mama-1-300x300.png","100x100":"https://darurialese.com/wp-content/uploads/2020/02/produs-mama-1-100x100.png"},"galerie":[{"full":"https://darurialese.com/wp-content/uploads/2019/02/WhatsApp-Image-2019-02-13-at-18.26.39.jpeg","300x300":"https://darurialese.com/wp-content/uploads/2019/02/WhatsApp-Image-2019-02-13-at-18.26.39-300x300.jpeg","100x100":"https://darurialese.com/wp-content/uploads/2019/02/WhatsApp-Image-2019-02-13-at-18.26.39-100x100.jpeg"},{"full":"https://darurialese.com/wp-content/uploads/2019/02/la-multi-ani-mama.png","300x300":"https://darurialese.com/wp-content/uploads/2019/02/la-multi-ani-mama-300x300.png","100x100":"https://darurialese.com/wp-content/uploads/2019/02/la-multi-ani-mama-100x100.png"}],"rating":"4.96","vanzari":1108,"dimensiune":{"lungime":"19","latime":"1","inaltime":"18"},"nr_recenzii":26,"average_recenzii":"4.96"},{"id":3238,"titlu":"Cadou personalizat Trofeu LED - Pentru mama Model 1","slug":"placheta-mama-led-model-1","descriere":"Esti in cautarea unui <a href=\"https://darurialese.ro/cadou/cadou-personalizat/\">cadou personalizat</a> de multumire pentru mama, dar esti in pana de idei? Noi iti oferim cadoul perfect, personalizat cu mesajul dorit, care va impresiona cu siguranta.\r\n\r\nMama- un singur cuvant, o mie de sentimente!\r\n\r\nNu cred ca un om atat de minunat poate fi descris doar in cateva cuvinte!\r\n\r\nEa este prima persoana pe care o vedem cand deschidem pentru intaia oara ochii! Zambetul gingas, privirea plina de iubire, fac parte din cel mai frumos chip pe care il vom avea alaturi toata viata!\r\n\r\nMama este persoana pe care nu o vom dezamagi niciodata! Indiferent de cate ori vom cadea, ea va fi acolo sa ne ridice. Ea va ramane intotdeauna fanul nostru numarul unu!\r\n\r\nViata nu vine cu un manual de instructiuni! Insa vine la pachet cu cel mai bun ghid pe care il putem avea. Mama este acolo sa ne invete sa vorbim, sa facem primii pasi si sa ne indrume cu intelepciune intotdeauna. Ea ne va educa si va fi acolo cu o vorba buna intotdeauna!\r\n\r\nSi acum, intrebarea cea mai buna este:\r\n<h5>Cum am putea alege un cadou personalizat de multumire potrivit, pentru o asemenea persoana, pentru mama?</h5>\r\nRaspunsul este simplu.\r\n\r\nUn cadou daruit din suflet, este cel mai bun cadou! Si ce poate fi mai de suflet decat o placheta personalizata, cu un mesaj special de multumire pentru mama? Pe aceasta placheta puteti grava un gand bun, o mica povestioara sau o urare ce vine din adancul sufletului vostru! Sau.. puteti lasa chiar si mesajul existent, daca va place! Ideea este ca, orice decizie ati lua, va fi un cadou de multumire pentru mama pe cinste!\r\n\r\nNu te poti decide in legatura cu o culoare anume? Stai fara grija! Acest model vine la pachet cu toate cele 3 culori: rosu, albastru si mov! Acestea se pot modifica din intrerupatorul atasat firului de priza.\r\n<h5>Inca nu te-am convins?</h5>\r\nAtunci poti vedea parerea integrala a clientilor care deja au achizitionat acest minunat cadou personalizat de multumire pentru mama de la noi pe <a href=\"https://facebook.com/darurialese\">Daruri Alese</a>\r\n\r\nTe asteptam cu drag!","descriere_scurta":"","pret":"115","pret_redus":"104","end_sale":"2026-01-31 23:59:59","imagine_principala":{"full":"https://darurialese.com/wp-content/uploads/nano-banana/LEDARIPI-MAMA/cadou_personalizat_trofeu_led_8211_pentru_mama_model_1_albastru.png","300x300":"https://darurialese.com/wp-content/uploads/nano-banana/LEDARIPI-MAMA/cadou_personalizat_trofeu_led_8211_pentru_mama_model_1_albastru-300x300.png","100x100":"https://darurialese.com/wp-content/uploads/nano-banana/LEDARIPI-MAMA/cadou_personalizat_trofeu_led_8211_pentru_mama_model_1_albastru-150x150.png"},"galerie":[{"full":"https://darurialese.com/wp-content/uploads/2018/11/trofeu-mama-mov.png","300x300":"https://darurialese.com/wp-content/uploads/2018/11/trofeu-mama-mov-300x300.png","100x100":"https://darurialese.com/wp-content/uploads/2018/11/trofeu-mama-mov-300x300.png"},{"full":"https://darurialese.com/wp-content/uploads/2018/11/trofeu-mama-rosu.png","300x300":"https://darurialese.com/wp-content/uploads/2018/11/trofeu-mama-rosu-300x300.png","100x100":"https://darurialese.com/wp-content/uploads/2018/11/trofeu-mama-rosu-100x100.png"},{"full":"https://darurialese.com/wp-content/uploads/nano-banana/LEDARIPI-MAMA/cadou_personalizat_trofeu_led_8211_pentru_mama_model_1_poza_luminata.png","300x300":"https://darurialese.com/wp-content/uploads/nano-banana/LEDARIPI-MAMA/cadou_personalizat_trofeu_led_8211_pentru_mama_model_1_poza_luminata-300x300.png","100x100":"https://darurialese.com/wp-content/uploads/nano-banana/LEDARIPI-MAMA/cadou_personalizat_trofeu_led_8211_pentru_mama_model_1_poza_luminata-150x150.png"},{"full":"https://darurialese.com/wp-content/uploads/nano-banana/LEDARIPI-MAMA/cadou_personalizat_trofeu_led_8211_pentru_mama_model_1_rosu.png","300x300":"https://darurialese.com/wp-content/uploads/nano-banana/LEDARIPI-MAMA/cadou_personalizat_trofeu_led_8211_pentru_mama_model_1_rosu-300x300.png","100x100":"https://darurialese.com/wp-content/uploads/nano-banana/LEDARIPI-MAMA/cadou_personalizat_trofeu_led_8211_pentru_mama_model_1_rosu-150x150.png"},{"full":"https://darurialese.com/wp-content/uploads/nano-banana/LEDARIPI-MAMA/cadou_personalizat_trofeu_led_8211_pentru_mama_model_1_verde.png","300x300":"https://darurialese.com/wp-content/uploads/nano-banana/LEDARIPI-MAMA/cadou_personalizat_trofeu_led_8211_pentru_mama_model_1_verde-300x300.png","100x100":"https://darurialese.com/wp-content/uploads/nano-banana/LEDARIPI-MAMA/cadou_personalizat_trofeu_led_8211_pentru_mama_model_1_verde-150x150.png"},{"full":"https://darurialese.com/wp-content/uploads/nano-banana/LEDARIPI-MAMA/cadou_personalizat_trofeu_led_8211_pentru_mama_model_1_mov.png","300x300":"https://darurialese.com/wp-content/uploads/nano-banana/LEDARIPI-MAMA/cadou_personalizat_trofeu_led_8211_pentru_mama_model_1_mov-300x300.png","100x100":"https://darurialese.com/wp-content/uploads/nano-banana/LEDARIPI-MAMA/cadou_personalizat_trofeu_led_8211_pentru_mama_model_1_mov-150x150.png"},{"full":"https://darurialese.com/wp-content/uploads/2018/11/trofeu-mama-albastru.png","300x300":"https://darurialese.com/wp-content/uploads/2018/11/trofeu-mama-albastru-300x300.png","100x100":"https://darurialese.com/wp-content/uploads/2018/11/trofeu-mama-albastru-100x100.png"}],"rating":"4.92","vanzari":1106,"dimensiune":{"lungime":"18.5","latime":"1","inaltime":"15.5"},"nr_recenzii":38,"average_recenzii":"4.92"},{"id":3307,"titlu":"Cadou personalizat Trofeu - Declaratie iubire","slug":"cadou-personalizat-trofeu-declaratie-iubire","descriere":"Esti in cautarea unui <a href=\"https://darurialese.ro/cadou/cadou-personalizat/\">cadou personalizat</a> pentru persoana iubita? Iti sarim in ajutor cu un trofeu personalizat care reprezinta o declaratie de iubire care va fi o surpriza placuta.\r\n\r\nCateodata, nu iti gasesti cuvintele potrivite care sa reprezinte sentimentele pentru persoana iubita. Ne-am gandit la asta si iti oferim la dispozitie acest cadou personalizat persoana iubita. Gestul tau va fi apreciat si va fi o amintire frumoasa pentru toata viata!\r\n<h5>Cauti un cadou pentru ziua indragostitilor, aniversarea relatiei sau pur si simplu vrei sa ii oferi persoanei iubire o declaratie de dragoste?</h5>\r\nAi venit in locul potrivit! Te ajutam acest model care iti pune la dispozitie un mesaj  emotionant, care sigur o va impresiona. Mai mult de atat, daca doresti sa ii faci o declaratie unica, scrisa din sufletul tau, putem personaliza cu mesajul dorit. In acest mod, este transformat intr-un cadou de suflet, simbolic pentru dragostea voastra.\r\n\r\nPersoana iubita este cea care iti este alaturi indiferent de situatie, te sprijina si ofera o mana de ajutor cand te afli la capatul puterilor. Te ajutam sa iti arati recunostinta fata de aceasta prin aceasta declaratie de dragoste impresionanta.\r\n\r\nCel mai interesant detaliu al produsului este faptul ca poti adauga fotografia voastra preferata, care sa cuprinda un moment special din viata voastra. Suntem siguri ca sufletul tau pereche va fi profund impresionat de acest trofeu personalizat atunci cand va primi cadoul.\r\n\r\nMai mult decat atat, livram cadoul oriunde in tara. Pentru a ne asigura ca oriunde v-ati afla, puteti transmite sentimentele dumneavoastra persoanei iubite.\r\n\r\nVezi parerea integrala a clientilor care deja au achizitionat un cadou personalizat pentru persoana iubita de la noi pe <a href=\"https://facebook.com/darurialese\">Daruri Alese.</a>","descriere_scurta":"Esti in cautarea unui <a href=\"https://darurialese.ro/cadou/cadou-personalizat/\">cadou personalizat</a> pentru persoana iubita? Iti sarim in ajutor cu un trofeu personalizat care reprezinta o declaratie de iubire care va fi o surpriza placuta.","pret":"110","pret_redus":null,"end_sale":null,"imagine_principala":{"full":"https://darurialese.com/wp-content/uploads/2019/01/222222-1200x1200.jpg","300x300":"https://darurialese.com/wp-content/uploads/2019/01/222222-1200x1200-300x300.jpg","100x100":"https://darurialese.com/wp-content/uploads/2019/01/222222-1200x1200-100x100.jpg"},"galerie":[],"rating":"4.94","vanzari":627,"dimensiune":{"lungime":"18","latime":"1","inaltime":"22"},"nr_recenzii":17,"average_recenzii":"4.94"},{"id":3078,"titlu":"Cadou personalizat Trofeu - Multumesc!","slug":"placheta-rotunda-multumesc","descriere":"<h3>Personalizează-l pentru a-l face unic</h3>\r\nFlexibilitatea acestui trofeu îți permite să îl personalizezi pentru orice ocazie. Fie că dorești să adaugi un mesaj de felicitare, să celebrezi o aniversare sau să comemorezi un eveniment special, acest trofeu poate fi adaptat pentru a se potrivi perfect nevoilor tale. Personalizarea poate include text, logo-uri, date sau chiar imagini simple, transformând acest trofeu într-un cadou cu adevărat unic și memorabil.","descriere_scurta":"<h3><strong>Un trofeu clasic și elegant pentru momentele tale speciale</strong></h3>\r\nAcest trofeu personalizat este alegerea perfectă pentru a marca orice ocazie importantă. Realizat din lemn și wenge, trofeul are o formă clasică, rotundă, care îmbină eleganța tradițională cu un stil modern. Este un cadou ideal pentru a celebra realizările, aniversările sau orice moment special din viața ta sau a celor dragi.","pret":"75","pret_redus":null,"end_sale":null,"imagine_principala":{"full":"https://darurialese.com/wp-content/uploads/2020/02/produs-multumesc.png","300x300":"https://darurialese.com/wp-content/uploads/2020/02/produs-multumesc-300x300.png","100x100":"https://darurialese.com/wp-content/uploads/2020/02/produs-multumesc-100x100.png"},"galerie":[{"full":"https://darurialese.com/wp-content/uploads/2018/05/33462576_1870817776296801_3516931423413993472_n.jpg","300x300":"https://darurialese.com/wp-content/uploads/2018/05/33462576_1870817776296801_3516931423413993472_n-300x300.jpg","100x100":"https://darurialese.com/wp-content/uploads/2018/05/33462576_1870817776296801_3516931423413993472_n-100x100.jpg"}],"rating":"4.63","vanzari":607,"dimensiune":{"lungime":"12","latime":"1","inaltime":"14"},"nr_recenzii":8,"average_recenzii":"4.63"},{"id":76700,"titlu":"Cadou personalizat -  mama fiica","slug":"cadou-personalizat-special-pentru-mama","descriere":"Esti in cautarea unui <a href=\"https://darurialese.ro/cadou/cadou-personalizat/\">trofeu personalizat</a> cu poza pentru mama? Te ajutam cu un cadou personalizat cu poza preferata si un mesaj prin care sa o surprinzi.\r\n\r\nVezi parerea clientilor care deja au achizitionat un trofeu personalizat cu poza pentru mama de la noi pe <a href=\"https://facebook.com/darurialese\">Daruri Alese.</a>","descriere_scurta":"","pret":"120","pret_redus":"104","end_sale":"2026-01-31 23:59:59","imagine_principala":{"full":"https://darurialese.com/wp-content/uploads/2020/05/88189365_2958407714204463_6418009805536886784_o.jpg","300x300":"https://darurialese.com/wp-content/uploads/2020/05/88189365_2958407714204463_6418009805536886784_o-300x300.jpg","100x100":"https://darurialese.com/wp-content/uploads/2020/05/88189365_2958407714204463_6418009805536886784_o-100x100.jpg"},"galerie":[],"rating":"5.00","vanzari":543,"dimensiune":{"lungime":"17","latime":"1","inaltime":"19"},"nr_recenzii":20,"average_recenzii":"5.00"}]},{"id":1352,"titlu":"Cadouri pentru sotie","slug":"cadouri-pentru-sotie","imagine":"https://darurialese.ro/wp-content/uploads/2022/05/mama-01.svg","produse":[{"id":3442,"titlu":"Cadou personalizat Trofeu - Tu esti tot ce am nevoie","slug":"cadou-personalizat-trofeu-esti-tot-ce-am-nevoie","descriere":"Esti in cautarea unui <a href=\"https://darurialese.ro/cadou/cadou-personalizat/\">cadou personalizat</a> pentru ziua indragostitilor? Te putem ajuta cu un trofeu personalizat pentru persoana iubita, cu un mesaj care va impresiona cu siguranta.\r\n\r\nZiua indragostitilor este momentul ideal sa iti surprinzi persoana iubita cu un cadou simbolic. Venim in ajutorul tau cu un trofeu personalizat cu un mesaj care sa ii ajunga la suflet, sa surprinda si sa emotioneze.  Mesajul poate fi modificat daca doresti sa transmiti o traire unica traita in doi, un detaliu simbolic pentru relatia voastra.\r\n\r\nAcest trofeu personalizat este un mod ideal de a-i arata persoanei care iti este alaturi la bine si greu, cat de mult inseamna pentru tine. Indiferent ca este ziua indragostitilor, aniversarea relatiei sau pur si simplu sa-i amintesti cat de importanta este. Suntem siguri ca reactia la primirea unui cadou personalizat ziua indragostitilor va fi una pe masura asteptarilor dumneavoastra.\r\n\r\nNu exista o dragoste mai frumoasa decat cea care vine din partea persoanei care te iubeste cu adevarat si ii pasa de tine. Te ajutam sa iti exprimi recunostinta si iubirea, oferindu-i un cadou personalizat. Acest trofeu poate fi unul simbolic, personalizat cu declaratia ta de dragoste scrisa din suflet.\r\n<h5>Aminteste-i iubitului/sotului ca este singurul lucru de care ai nevoie din viata ta, pentru a fi completa. Acest mesaj, cu singuranta il va impresiona.</h5>\r\nOrice persoana care se afla intr-o relatie, simte nevoia sa i se dovedeaca ca este iubita si apreciata. Un cadou personalizat este modalitatea perfecta prin care sa ii amintesti cat de mult inseamna pentru tine si sentimentele tale de iubire neconditionata.\r\n\r\nLivram acest cadou special, oriunde in tara, direct la usa locuintei tale. Asa iti poti impresiona iubita din orice regiune a tarii noastre.\r\n\r\n&nbsp;\r\n\r\nPoti vedea parerea clientilor care deja au achizitionat un cadou personalizat pentru ziua indragostitilor de la noi pe <a href=\"https://facebook.com/darurialese\">Daruri Alese.</a>","descriere_scurta":"","pret":"85","pret_redus":null,"end_sale":null,"imagine_principala":{"full":"https://darurialese.com/wp-content/uploads/2020/02/produs-esti-tot-ce-am.png","300x300":"https://darurialese.com/wp-content/uploads/2020/02/produs-esti-tot-ce-am-300x300.png","100x100":"https://darurialese.com/wp-content/uploads/2020/02/produs-esti-tot-ce-am-100x100.png"},"galerie":[{"full":"https://darurialese.com/wp-content/uploads/2019/07/p4-1200x1200.jpg","300x300":"https://darurialese.com/wp-content/uploads/2019/07/p4-1200x1200-300x300.jpg","100x100":"https://darurialese.com/wp-content/uploads/2019/07/p4-1200x1200-100x100.jpg"}],"rating":"5.00","vanzari":448,"dimensiune":{"lungime":"14","latime":"1","inaltime":"15"},"nr_recenzii":11,"average_recenzii":"5.00"},{"id":348424,"titlu":"Trofeu personalizat cu Licheni - Cadou indragostiti inimioare","slug":"trofeu-personalizat-cu-licheni-cadou-indragostiti-inimioare","descriere":"<h3>Transmite sentimentele într-un mod unic</h3>\r\nDesignul trofeului în formă de inimă este atât estetic, cât și plin de semnificație, reprezentând dragostea și conexiunea dintre voi. Lichenii roșii adaugă o notă de culoare și vitalitate, în timp ce lemnul wenge și plexiglass-ul creează un contrast vizual plăcut. Spațiul pentru două fotografii îți permite să personalizezi trofeul cu momente speciale petrecute împreună, transformându-l într-un cadou cu adevărat unic.","descriere_scurta":"<h3><strong>Exprimă-ți dragostea cu un trofeu unic și personalizat</strong></h3>\r\nPentru a-ți arăta dragostea și aprecierea față de persoana iubită, alege acest trofeu personalizat în formă de inimă. Realizat din lemn wenge, plexiglass și licheni roșii, acest trofeu combină naturalețea cu un design contemporan, fiind ideal pentru a simboliza dragostea și pasiunea pe care o împărtășiți. Cu spațiu pentru două fotografii, acest trofeu devine un cadou personal, perfect pentru a celebra iubirea voastră.","pret":"145","pret_redus":null,"end_sale":null,"imagine_principala":{"full":"https://darurialese.com/wp-content/uploads/2022/05/trofeu-personalizat-cu-licheni-cadou-indragostiti-inimioare.jpeg","300x300":"https://darurialese.com/wp-content/uploads/2022/05/trofeu-personalizat-cu-licheni-cadou-indragostiti-inimioare-300x300.jpeg","100x100":"https://darurialese.com/wp-content/uploads/2022/05/trofeu-personalizat-cu-licheni-cadou-indragostiti-inimioare-150x150.jpeg"},"galerie":[],"rating":"5.00","vanzari":283,"dimensiune":{"lungime":"23.5","latime":"1","inaltime":"17.5"},"nr_recenzii":19,"average_recenzii":"5.00"},{"id":173545,"titlu":"Trofeu personalizat - Cadou cu licheni pentru persoana iubita","slug":"trofeu-personalizat-cu-licheni-pentru-persoana-iubita","descriere":"<h3>Trofeu personalizat cu licheni – creează un cadou inedit pentru o persoană dragă</h3>\r\nO modalitatea grozavă de a-i arăta persoanei iubite cât de mult o iubești, este să-i oferi un trofeu personalizat cu licheni. Trofeul este confecționat din materiale rezistente și mușchi licheni, cu poza cuplului printată și un text gravat prin care să îți exprimi sentimentele. Aceast produs este realizat la comandă doar pentru destinatar cu designul tău preferat. În plus, un trofeul cu licheni reprezintă un cadou minunat care va dura mult timp în viitor.\r\n\r\n&nbsp;","descriere_scurta":"<h2>Trofeu personalizat cu licheni pentru persoana iubită – un mod unic de a-ți arăta dragostea</h2>\r\nDacă ești în căutarea unui mod unic de a-ți arăta dragostea, Daruri Alese îți propune un trofeu personalizat cu licheni, gravat cu vorbe alese. Dacă dorești ceva cu adevărat unic și special pentru persoana iubită, atunci cu siguranță ar trebui să-i oferi un trofeu cu licheni personalizat. Este elegant, cu elemente decorative interesante și naturale și îi va arăta persoanei iubite cât de mult îți pasă de ea și de relația dintre voi.","pret":"135","pret_redus":null,"end_sale":null,"imagine_principala":{"full":"https://darurialese.com/wp-content/uploads/2021/01/trofeu-personalizat-persoana-iubita.jpg","300x300":"https://darurialese.com/wp-content/uploads/2021/01/trofeu-personalizat-persoana-iubita-300x300.jpg","100x100":"https://darurialese.com/wp-content/uploads/2021/01/trofeu-personalizat-persoana-iubita-100x100.jpg"},"galerie":[],"rating":"5.00","vanzari":264,"dimensiune":{"lungime":"17","latime":"1","inaltime":"18"},"nr_recenzii":14,"average_recenzii":"5.00"},{"id":3170,"titlu":"Cadou personalizat Trofeu - Inimioara si Ingerasi","slug":"placheta-personalizata-inimiora-si-ingerasi","descriere":"<h2>Cadoul perfect pentru momente de neuitat</h2>\r\nAlege să oferi un cadou personalizat care să aducă un zâmbet pe chipul celor dragi. Trofeul din pfl wenge și plexiglas, cu dimensiunile de 12x14.3 cm, reprezintă un simbol al iubirii și aprecierii, fiind ideal pentru ocazii speciale precum aniversări sau zile de naștere. Detaliile cu inimioară și îngerași evocă sentimente de afecțiune și sensibilitate, transformând fiecare moment într-un cadou unic. Feedback-ul pozitiv din partea celor care l-au achiziționat dovedește că acest trofeu este cu adevărat special și va rămâne mereu în amintirile celor care îl primesc.","descriere_scurta":"<h2>Oferă un cadou cu suflet</h2>\r\nAlege să îți exprimi iubirea sau aprecierea într-un mod cu totul special. Un cadou personalizat, precum acest trofeu cu inimioară și îngerași, este alegerea perfectă pentru a marca ocazii importante, fie că este vorba despre aniversări, zile de naștere sau sărbători de neuitat. Este un simbol elegant al sentimentelor tale, menit să dăruiești momente de bucurie celor dragi.","pret":"80","pret_redus":null,"end_sale":null,"imagine_principala":{"full":"https://darurialese.com/wp-content/uploads/2020/02/placheta-personalizata-inimiora-si-ingerasi.png","300x300":"https://darurialese.com/wp-content/uploads/2020/02/placheta-personalizata-inimiora-si-ingerasi-300x300.png","100x100":"https://darurialese.com/wp-content/uploads/2020/02/placheta-personalizata-inimiora-si-ingerasi-150x150.png"},"galerie":[],"rating":"5.00","vanzari":258,"dimensiune":{"lungime":"14.3","latime":"1","inaltime":"12"},"nr_recenzii":9,"average_recenzii":"5.00"},{"id":3301,"titlu":"Cadou personalizat Trofeu - Esti tot ce am","slug":"placheta-iubire-esti-tot-ce-am","descriere":"Esti in cautarea unui <a href=\"https://darurialese.ro/cadou/cadou-personalizat/\">cadou personalizat</a> pentru aniversare relatie? Te putem ajuta cu un trofeu personalizat pentru persoana iubita, care va fi o surpriza placuta cu siguranta.\r\n\r\nOrice aniversare trebuie sa fie insotita de un gest romantic care sa dovedeasca ca iubirea rezista in timp. De aceea, un trofeu personalizat, ar fi cadoul ideal care sa dovedeasca ca flacara iubirii voastre ramane vie in timp.\r\n\r\nEste foarte dificil sa alegi un cadou care se simbolizeze exact ce simti. Din text motiv, trofeul poate fi personalizat cu mesajul dumnevoastra, care sa exprime exact sentimentele unice pe care le traiti.\r\n\r\nVezi parerea clientilor care deja au achizitionat un cadou personalizat pentru aniversare relatie de la noi pe <a href=\"https://facebook.com/darurialese\">Daruri Alese.</a>","descriere_scurta":"","pret":"110","pret_redus":null,"end_sale":null,"imagine_principala":{"full":"https://darurialese.com/wp-content/uploads/2020/02/produs-esti-tot-ce-am-nevoie.png","300x300":"https://darurialese.com/wp-content/uploads/2020/02/produs-esti-tot-ce-am-nevoie-300x300.png","100x100":"https://darurialese.com/wp-content/uploads/2020/02/produs-esti-tot-ce-am-nevoie-100x100.png"},"galerie":[{"full":"https://darurialese.com/wp-content/uploads/2019/01/estitot2-1200x1200.jpg","300x300":"https://darurialese.com/wp-content/uploads/2019/01/estitot2-1200x1200-300x300.jpg","100x100":"https://darurialese.com/wp-content/uploads/2019/01/estitot2-1200x1200-100x100.jpg"},{"full":"https://darurialese.com/wp-content/uploads/2019/01/estitot-1200x1200.jpg","300x300":"https://darurialese.com/wp-content/uploads/2019/01/estitot-1200x1200-300x300.jpg","100x100":"https://darurialese.com/wp-content/uploads/2019/01/estitot-1200x1200-100x100.jpg"}],"rating":"5.00","vanzari":235,"dimensiune":{"lungime":"21","latime":"1","inaltime":"17.5"},"nr_recenzii":11,"average_recenzii":"5.00"}]}]}